mkmsg/__init__.py
mkmsg/MK_code/generate_otp.py
mkmsg/MK_code/send_html_mail.py
mkmsg/MK_code/send_mail.py
mkmsg/MK_code/send_whats_msg.py
mkmsg-0.1.3.dist-info/licenses/LICENSE.txt
mkmsg-0.1.3.dist-info/METADATA
mkmsg-0.1.3.dist-info/WHEEL
mkmsg-0.1.3.dist-info/top_level.txt
mkmsg-0.1.3.dist-info/RECORD
