Metadata-Version: 2.4
Name: mkmsg
Version: 0.1.3
Summary: Python library to send WhatsApp messages, emails, HTML emails, and generate OTPs
Author-email: Mohamed Khaled <mk.programmed@gmail.com>
License: MIT
Keywords: whatsapp,email,otp,messaging
Classifier: Programming Language :: Python :: 3
Classifier: License :: OSI Approved :: MIT License
Classifier: Operating System :: OS Independent
Requires-Python: >=3.7
License-File: LICENSE.txt
Dynamic: license-file
